{
  "host": "localhost",
  "port": 3030,
  "public": "../public/",
  "paginate": {
    "default": 10,
    "max": 50
  },
  "cloudinary": {
    "cloud_name": "<cloud name>",
    "api_key": "<api key>",
    "api_secret": "<api secret>"
  },
  "twilio": {
    "accountSid": "<account sid>",
    "authToken": "<auth token>",
    "twilio_number": "<number>"
  },
  "mysql": "mysql://root@localhost:3306/fiesta",
  "authentication": {
    "secret": "wazwiti",
    "strategies": [
      "jwt",
      "google"
    ],
    "path": "/authentication",
    "service": "users",
    "jwt": {
      "header": {
        "typ": "access"
      },
      "audience": "https://yourdomain.com",
      "subject": "anonymous",
      "issuer": "feathers",
      "algorithm": "HS256",
      "expiresIn": "1d"
    },
    "cookie": {
      "enabled": true,
      "name": "feathers-jwt",
      "httpOnly": false,
      "secure": false
    }
  }
}
